tiktokx/__init__.py
tiktokx/model.py
tiktokx/train.py
tiktokx/utils.py
tiktokx-0.1.4.dist-info/LICENSE
tiktokx-0.1.4.dist-info/WHEEL
tiktokx-0.1.4.dist-info/METADATA
tiktokx-0.1.4.dist-info/RECORD
