Metadata-Version: 2.1
Name: tiktokx
Version: 0.1.4
Summary: The rhythm of algorithms, dancing through recommendation streams.
Author: Kye Gomez
Author-email: kye@apac.ai
Classifier: Programming Language :: Python :: 2
Classifier: Programming Language :: Python :: 2.7
Classifier: Programming Language :: Python :: 3
Classifier: Programming Language :: Python :: 3.4
Classifier: Programming Language :: Python :: 3.5
Classifier: Programming Language :: Python :: 3.6
Classifier: Programming Language :: Python :: 3.7
Classifier: Programming Language :: Python :: 3.8
Classifier: Programming Language :: Python :: 3.9
Classifier: Programming Language :: Python :: 3.10
Classifier: Programming Language :: Python :: 3.11
Requires-Dist: dgl
Requires-Dist: numpy
Requires-Dist: scipy
Requires-Dist: torch
Requires-Dist: visdom
